<?xml version="1.0"?> <DOCUMENT xmlns="cocokms.xsd"><COCOKMS><HEADER><KD_DOK>5</KD_DOK><KD_TPS>1MUT</KD_TPS><NM_ANGKUT>INTERASIA PROGRESS</NM_ANGKUT><NO_VOY_FLIGHT>E095</NO_VOY_FLIGHT><CALL_SIGN>9V9662</CALL_SIGN><TGL_TIBA>20250213</TGL_TIBA><KD_GUDANG>1MUT</KD_GUDANG><REF_NUMBER>ITM00001/02/25-001</REF_NUMBER></HEADER><DETIL><KMS><NO_BL_AWB>PKGJKTSE2502-012-01</NO_BL_AWB><TGL_BL_AWB>20250211</TGL_BL_AWB><NO_MASTER_BL_AWB>KMTCPKG2563180</NO_MASTER_BL_AWB><TGL_MASTER_BL_AWB>20251002</TGL_MASTER_BL_AWB><ID_CONSIGNEE>43</ID_CONSIGNEE><CONSIGNEE>PT AGRO BUKIT</CONSIGNEE><BRUTO>1902.0000</BRUTO><NO_BC11>001591</NO_BC11><TGL_BC11>20250211</TGL_BC11><NO_POS_BC11/><CONT_ASAL>SEGU2509505</CONT_ASAL><SERI_KEMAS>1</SERI_KEMAS><KD_KEMAS>PK</KD_KEMAS><JML_KEMAS>4</JML_KEMAS><KD_TIMBUN/><KD_DOK_INOUT>3</KD_DOK_INOUT><NO_DOK_INOUT>003402</NO_DOK_INOUT><TGL_DOK_INOUT>20250214</TGL_DOK_INOUT><WK_INOUT>20250214172540</WK_INOUT><KD_SAR_ANGKUT_INOUT>1</KD_SAR_ANGKUT_INOUT><NO_POL/><PEL_MUAT>MYPKG</PEL_MUAT><PEL_TRANSIT/><PEL_BONGKAR/><GUDANG_TUJUAN>1MUT</GUDANG_TUJUAN><KODE_KANTOR>040300</KODE_KANTOR><NO_DAFTAR_PABEAN/><TGL_DAFTAR_PABEAN/><NO_SEGEL_BC/><TGL_SEGEL_BC/><NO_IJIN_TPS/><TGL_IJIN_TPS/><NAMA_CONSOLIDATOR>PT INTI MANDIRI UTAMA TRANS</NAMA_CONSOLIDATOR><NPWP_CONSOLIDATOR>0022383483042000</NPWP_CONSOLIDATOR><ALAMAT_CONSOLIDATOR>Jl. Bugis Raya No. 15 Kebon Bawang Tanjung Priok</ALAMAT_CONSOLIDATOR></KMS></DETIL></COCOKMS></DOCUMENT>